[
  {
    "name": "Apprentice Wizard",
    "guardian": {
      "rarity": "Ordinary",
      "type": "Minion",
      "rulesText": "Spellcaster\r\n\r\nGenesis → Draw a spell.",
      "cost": 3,
      "attack": 1,
      "defence": 1,
      "life": null,
      "thresholds": {
        "air": 1,
        "earth": 0,
        "fire": 0,
        "water": 0
      }
    },
    "elements": "Air",
    "subTypes": "Mortal",
    "sets": [
      {
        "name": "Alpha",
        "releasedAt": "2023-04-19T00:00:00.000Z",
        "metadata": {
          "rarity": "Ordinary",
          "type": "Minion",
          "rulesText": "Spellcaster\n\nGenesis → Draw a spell.",
          "cost": 3,
          "attack": 1,
          "defence": 1,
          "life": null,
          "thresholds": {
            "air": 1,
            "earth": 0,
            "fire": 0,
            "water": 0
          }
        },
        "variants": [
          {
            "slug": "alp_apprentice_wizard_b_s",
            "finish": "Standard",
            "product": "Booster",
            "artist": "Ossi Hiekkala",
            "flavorText": "",
            "typeText": "An Ordinary Mortal new to power"
          },
          {
            "slug": "alp_apprentice_wizard_d_s",
            "finish": "Standard",
            "product": "Preconstructed_Deck",
            "artist": "Ossi Hiekkala",
            "flavorText": "",
            "typeText": "An Ordinary Mortal new to power"
          },
          {
            "slug": "alp_apprentice_wizard_b_f",
            "finish": "Foil",
            "product": "Booster",
            "artist": "Ossi Hiekkala",
            "flavorText": "",
            "typeText": "An Ordinary Mortal new to power"
          }
        ]
      },
      {
        "name": "Beta",
        "releasedAt": "2023-11-10T00:00:00.000Z",
        "metadata": {
          "rarity": "Ordinary",
          "type": "Minion",
          "rulesText": "Spellcaster\r\n\r\nGenesis → Draw a spell.",
          "cost": 3,
          "attack": 1,
          "defence": 1,
          "life": null,
          "thresholds": {
            "air": 1,
            "earth": 0,
            "fire": 0,
            "water": 0
          }
        },
        "variants": [
          {
            "slug": "bet_apprentice_wizard_b_s",
            "finish": "Standard",
            "product": "Booster",
            "artist": "Ossi Hiekkala",
            "flavorText": "",
            "typeText": "An Ordinary Mortal new to power"
          },
          {
            "slug": "bet_apprentice_wizard_b_f",
            "finish": "Foil",
            "product": "Booster",
            "artist": "Ossi Hiekkala",
            "flavorText": "",
            "typeText": "An Ordinary Mortal new to power"
          }
        ]
      }
    ]
  },
  {
    "name": "Blood Ravens",
    "guardian": {
      "rarity": "Ordinary",
      "type": "Minion",
      "rulesText": "Airborne\r\n \r\nDamage dealt by Blood Ravens' strikes heals you.",
      "cost": 1,
      "attack": 1,
      "defence": 1,
      "life": null,
      "thresholds": {
        "air": 1,
        "earth": 0,
        "fire": 0,
        "water": 0
      }
    },
    "elements": "Air",
    "subTypes": "Beast",
    "sets": [
      {
        "name": "Alpha",
        "releasedAt": "2023-04-19T00:00:00.000Z",
        "metadata": {
          "rarity": "Ordinary",
          "type": "Minion",
          "rulesText": "Airborne\n\nDamage dealt by Blood Ravens' strikes heals you.",
          "cost": 1,
          "attack": 1,
          "defence": 1,
          "life": null,
          "thresholds": {
            "air": 1,
            "earth": 0,
            "fire": 0,
            "water": 0
          }
        },
        "variants": [
          {
            "slug": "alp_blood_ravens_b_s",
            "finish": "Standard",
            "product": "Booster",
            "artist": "Michal Nagypál",
            "flavorText": "Dark wings bring dark winds.",
            "typeText": "A cruel conspiracy of Ordinary Beasts"
          },
          {
            "slug": "alp_blood_ravens_b_f",
            "finish": "Foil",
            "product": "Booster",
            "artist": "Michal Nagypál",
            "flavorText": "Dark wings bring dark winds.",
            "typeText": "A cruel conspiracy of Ordinary Beasts"
          }
        ]
      },
      {
        "name": "Beta",
        "releasedAt": "2023-11-10T00:00:00.000Z",
        "metadata": {
          "rarity": "Ordinary",
          "type": "Minion",
          "rulesText": "Airborne\r\n \r\nDamage dealt by Blood Ravens' strikes heals you.",
          "cost": 1,
          "attack": 1,
          "defence": 1,
          "life": null,
          "thresholds": {
            "air": 1,
            "earth": 0,
            "fire": 0,
            "water": 0
          }
        },
        "variants": [
          {
            "slug": "bet_blood_ravens_b_s",
            "finish": "Standard",
            "product": "Booster",
            "artist": "Michal Nagypál",
            "flavorText": "Dark wings bring dark winds.",
            "typeText": "A cruel conspiracy of Ordinary Beasts"
          },
          {
            "slug": "bet_blood_ravens_b_f",
            "finish": "Foil",
            "product": "Booster",
            "artist": "Michal Nagypál",
            "flavorText": "Dark wings bring dark winds.",
            "typeText": "A cruel conspiracy of Ordinary Beasts"
          }
        ]
      }
    ]
  },
  {
    "name": "Fade",
    "guardian": {
      "rarity": "Ordinary",
      "type": "Magic",
      "rulesText": "Give an allied minion Stealth. If it occupies an enemy site, draw a card.",
      "cost": 2,
      "attack": null,
      "defence": null,
      "life": null,
      "thresholds": {
        "air": 1,
        "earth": 0,
        "fire": 0,
        "water": 0
      }
    },
    "elements": "Air",
    "subTypes": "",
    "sets": [
      {
        "name": "Alpha",
        "releasedAt": "2023-04-19T00:00:00.000Z",
        "metadata": {
          "rarity": "Ordinary",
          "type": "Magic",
          "rulesText": "Give an allied minion Stealth. If it occupies an enemy site, draw a card.",
          "cost": 2,
          "attack": null,
          "defence": null,
          "life": null,
          "thresholds": {
            "air": 1,
            "earth": 0,
            "fire": 0,
            "water": 0
          }
        },
        "variants": [
          {
            "slug": "alp_fade_b_s",
            "finish": "Standard",
            "product": "Booster",
            "artist": "Elvira Shakirova",
            "flavorText": "I could pay, but then I'd just have to rob them again.",
            "typeText": "Ordinary Magic of covert concealment"
          },
          {
            "slug": "alp_fade_b_f",
            "finish": "Foil",
            "product": "Booster",
            "artist": "Elvira Shakirova",
            "flavorText": "I could pay, but then I'd just have to rob them again.",
            "typeText": "Ordinary Magic of covert concealment"
          }
        ]
      },
      {
        "name": "Beta",
        "releasedAt": "2023-11-10T00:00:00.000Z",
        "metadata": {
          "rarity": "Ordinary",
          "type": "Magic",
          "rulesText": "Give an allied minion Stealth. If it occupies an enemy site, draw a card.",
          "cost": 2,
          "attack": null,
          "defence": null,
          "life": null,
          "thresholds": {
            "air": 1,
            "earth": 0,
            "fire": 0,
            "water": 0
          }
        },
        "variants": [
          {
            "slug": "bet_fade_b_s",
            "finish": "Standard",
            "product": "Booster",
            "artist": "Elvira Shakirova",
            "flavorText": "I could pay, but then I'd just have to rob them again.",
            "typeText": "Ordinary Magic of covert concealment"
          },
          {
            "slug": "bet_fade_b_f",
            "finish": "Foil",
            "product": "Booster",
            "artist": "Elvira Shakirova",
            "flavorText": "I could pay, but then I'd just have to rob them again.",
            "typeText": "Ordinary Magic of covert concealment"
          }
        ]
      }
    ]
  },
  {
    "name": "Fields of Camlann",
    "guardian": {
      "rarity": "Unique",
      "type": "Site",
      "rulesText": "(F)(F)(F) – Genesis → Each player chooses one of their minions. Kill the rest.",
      "cost": null,
      "attack": null,
      "defence": null,
      "life": null,
      "thresholds": {
        "air": 0,
        "earth": 0,
        "fire": 1,
        "water": 0
      }
    },
    "elements": "Fire",
    "subTypes": "",
    "sets": [
      {
        "name": "Arthurian Legends",
        "releasedAt": "2024-10-04T00:00:00.000Z",
        "metadata": {
          "rarity": "Unique",
          "type": "Site",
          "rulesText": "(F)(F)(F) – Genesis → Each player chooses one of their minions. Kill the rest.",
          "cost": null,
          "attack": null,
          "defence": null,
          "life": null,
          "thresholds": {
            "air": 0,
            "earth": 0,
            "fire": 1,
            "water": 0
          }
        },
        "variants": [
          {
            "slug": "art_fields_of_camlann_b_s",
            "finish": "Standard",
            "product": "Booster",
            "artist": "Vasiliy Ermolaev",
            "flavorText": "",
            "typeText": "A Unique Site where fates are sealed"
          },
          {
            "slug": "art_fields_of_camlann_b_f",
            "finish": "Foil",
            "product": "Booster",
            "artist": "Vasiliy Ermolaev",
            "flavorText": "",
            "typeText": "A Unique Site where fates are sealed"
          }
        ]
      }
    ]
  },
  {
    "name": "The Colour Out of Space",
    "guardian": {
      "rarity": "Unique",
      "type": "Site",
      "rulesText": "Provides no mana or threshold if not adjacent to the void.",
      "cost": null,
      "attack": null,
      "defence": null,
      "life": null,
      "thresholds": {
        "air": 1,
        "earth": 1,
        "fire": 1,
        "water": 1
      }
    },
    "elements": "Earth, Fire, Water, Air",
    "subTypes": "",
    "sets": [
      {
        "name": "Alpha",
        "releasedAt": "2023-04-19T00:00:00.000Z",
        "metadata": {
          "rarity": "Unique",
          "type": "Site",
          "rulesText": "Provides no mana or threshold if not adjacent to the void.",
          "cost": null,
          "attack": null,
          "defence": null,
          "life": null,
          "thresholds": {
            "air": 1,
            "earth": 1,
            "fire": 1,
            "water": 1
          }
        },
        "variants": [
          {
            "slug": "alp_the_colour_out_of_space_b_s",
            "finish": "Standard",
            "product": "Booster",
            "artist": "Brian Smith",
            "flavorText": "",
            "typeText": "A Unique non-Euclidean Site"
          },
          {
            "slug": "alp_the_colour_out_of_space_b_f",
            "finish": "Foil",
            "product": "Booster",
            "artist": "Brian Smith",
            "flavorText": "",
            "typeText": "A Unique non-Euclidean Site"
          }
        ]
      },
      {
        "name": "Beta",
        "releasedAt": "2023-11-10T00:00:00.000Z",
        "metadata": {
          "rarity": "Unique",
          "type": "Site",
          "rulesText": "Provides no mana or threshold if not adjacent to the void.",
          "cost": null,
          "attack": null,
          "defence": null,
          "life": null,
          "thresholds": {
            "air": 1,
            "earth": 1,
            "fire": 1,
            "water": 1
          }
        },
        "variants": [
          {
            "slug": "bet_the_colour_out_of_space_b_s",
            "finish": "Standard",
            "product": "Booster",
            "artist": "Brian Smith",
            "flavorText": "",
            "typeText": "A Unique non-Euclidean Site"
          },
          {
            "slug": "bet_the_colour_out_of_space_b_f",
            "finish": "Foil",
            "product": "Booster",
            "artist": "Brian Smith",
            "flavorText": "",
            "typeText": "A Unique non-Euclidean Site"
          },
          {
            "slug": "bet_the_colour_out_of_space_p_f",
            "finish": "Foil",
            "product": "Promo",
            "artist": "Dan Seagrave",
            "flavorText": "",
            "typeText": "A Unique non-Euclidean Site"
          }
        ]
      }
    ]
  }
]
